ush.py
ush-4.1.0.dist-info/DESCRIPTION.rst
ush-4.1.0.dist-info/METADATA
ush-4.1.0.dist-info/RECORD
ush-4.1.0.dist-info/WHEEL
ush-4.1.0.dist-info/metadata.json
ush-4.1.0.dist-info/top_level.txt
