Metadata-Version: 2.0
Name: ush
Version: 4.1.0
Summary: Powerful API for invoking with external commands
Home-page: https://github.com/tarruda/python-ush
Author: Thiago de Arruda
Author-email: tpadilha84@gmail.com
License: MIT
Download-URL: https://github.com/tarruda/python-ush/archive/4.1.0.tar.gz
Keywords: sh,unix,bash,shell,glob
Platform: UNKNOWN
